<?xml version="1.0" encoding="UTF-8"?>
<userGroups xmlns:xsi="http://www.w3.org/2001/XMLSchema-instance" xsi:schemaLocation="http://www.wldelft.nl/fews http://fews.wldelft.nl/schemas/version1.0/userGroups.xsd" xmlns="http://www.wldelft.nl/fews">
	<userGroup id="DataEntry">
		<!-- MDBA work accounts -->
		<user id="dn4"/>
		<user id="gg"/>
		<user id="ta1"/>
		<user id="AB10"/>
		<!-- MDBA private accounts -->
		<user id="$Peter$"/>
		<user id="$HOME_USER_ACCOUNT$"/>
		<!-- Deltares employees -->
		<user id="kleerma"/>
		<user id="gijsber"/>
		<user id="miltenbu"/>
		<userGroup id="Administrators"/>
		<userGroup id="RiverOperator"/>
	</userGroup>
	<userGroup id="RiverOperator">
		<user id="rmw"/>
		<user id="prs"/>
		<user id="awb"/>
		<user id="am4"/>
		<user id="tz"/>
		<user id="jpd"/>
		<user id="wl1"/>
		<user id="sk1"/>
		<user id="klg"/>
		<user id="lm2"/>
		<user id="jw"/>
		<user id="ng1"/>
		<user id="jh10"/>
		<user id="sg3"/>
		<user id="ar2"/>
		<user id="aa"/>
		<user id="axk"/>
		<user id="jgf"/>
		<user id="tj1"/>
		<user id="eu10"/>
		<user id="aj1"/>
		<user id="dk"/>
		<user id="sc"/>
		<user id="wl10"/>
		<user id="gb10"/>
		<user id="kjt"/>
		<user id="js3"/>
		<user id="tr10"/>
	</userGroup>
	<userGroup id="Forecaster">
		<user id="$HOME_USER_ACCOUNT$"/>
		<userGroup id="RiverOperator"/>
		<userGroup id="Administrators"/>
	</userGroup>
	<userGroup id="Administrators">
		<user id="ll"/>
		<user id="rs1"/>
		<user id="ds12"/>
		<user id="service_rows"/>
		<!-- Deltares employees -->
		<user id="gijsber"/>
		<user id="kleerma"/>
		<user id="miltenbu"/>
	</userGroup>
</userGroups>