<?xml version="1.0" encoding="UTF-8"?>
<script xmlns="http://www.wldelft.nl/fews" xmlns:xsi="http://www.w3.org/2001/XMLSchema-instance" xsi:schemaLocation="http://www.wldelft.nl/fews http://fews.wldelft.nl/watercoachschemas/version1.0/script_config.xsd">
	<title>MDBA Data Entry training</title>
	<timeZone>
		<offset>+10:00</offset>
	</timeZone>
	<dataStart date="2016-10-01" time="00:00:00"/>
	<dataStop date="2016-10-11" time="00:00:00"/>
	<stories>
		<inbox>
			<title>inbox</title>
			<frame>
				<title>Start of the training</title>
				<start date="2016-10-01" time="00:00:00"/>
				<popup>false</popup>
				<message>The training has started, have fun.</message>
			</frame>
			<frame>
				<title>T1</title>
				<start date="2016-10-01" time="01:00:00"/>
			</frame>
			<frame>
				<title>T2</title>
				<start date="2016-10-01" time="02:00:00"/>
			</frame>
			<frame>
				<title>T3</title>
				<start date="2016-10-01" time="03:00:00"/>
			</frame>
			<frame>
				<title>T4</title>
				<start date="2016-10-01" time="04:00:00"/>
			</frame>
			<frame>
				<title>T5</title>
				<start date="2016-10-01" time="05:00:00"/>
			</frame>
		</inbox>
	</stories>
</script>
